bris_fiab/__init__.py
bris_fiab/anemoi_plugins/inference/apply_adiabatic_corrections/__init__.py
bris_fiab/anemoi_plugins/inference/apply_adiabatic_corrections/adiabatic_correct.py
bris_fiab/anemoi_plugins/inference/apply_adiabatic_corrections/adiabatic_correct_test.py
bris_fiab/anemoi_plugins/inference/apply_adiabatic_corrections/apply_adiabatic_corrections.py
bris_fiab/anemoi_plugins/inference/apply_adiabatic_corrections/apply_adiabatic_corrections_test.py
bris_fiab/anemoi_plugins/inference/apply_adiabatic_corrections/test_data/1.grib
bris_fiab/anemoi_plugins/inference/apply_adiabatic_corrections/test_data/2.grib
bris_fiab/anemoi_plugins/inference/downscale/__init__.py
bris_fiab/anemoi_plugins/inference/downscale/downscale.py
bris_fiab/checkpoint/elevation.py
bris_fiab/checkpoint/graph.py
bris_fiab/checkpoint/interpolate.py
bris_fiab/checkpoint/make_graph.py
bris_fiab/checkpoint/metadata.py
bris_fiab/checkpoint/update.py
bris_fiab/orography/download.py
bris_fiab-0.1.1.dist-info/licenses/LICENSE
bris_fiab-0.1.1.dist-info/METADATA
bris_fiab-0.1.1.dist-info/WHEEL
bris_fiab-0.1.1.dist-info/entry_points.txt
bris_fiab-0.1.1.dist-info/top_level.txt
bris_fiab-0.1.1.dist-info/RECORD
