Metadata-Version: 2.4
Name: bris-fiab
Version: 0.1.1
Summary: Running the bris model in Forecast-in-a-Box and anemoi-inference
License-Expression: Apache-2.0
Project-URL: Homepage, https://github.com/metno/bris-fiab
Project-URL: Issues, https://github.com/metno/bris-fiab/issues
Classifier: Programming Language :: Python :: 3
Classifier: Operating System :: OS Independent
Requires-Python: >=3.11
License-File: LICENSE
Requires-Dist: anemoi-datasets
Requires-Dist: anemoi-graphs
Requires-Dist: anemoi-inference
Requires-Dist: anemoi-models==0.9.5
Requires-Dist: metpy>=1.7.1
Requires-Dist: anemoi-transform
Requires-Dist: anemoi-utils
Requires-Dist: ecmwf-api-client
Requires-Dist: pydantic>=2.11.7
Requires-Dist: pytest>=8.4.1
Requires-Dist: rioxarray>=0.19.0
Requires-Dist: scipy>=1.16.1
Requires-Dist: trimesh>=4.7.3
Requires-Dist: pyyaml>=6.0.1
Requires-Dist: metpy>=1.7.1
Requires-Dist: twine>=6.2.0
Requires-Dist: torch-geometric==2.4.0
Dynamic: license-file
